tap_socketdev/__init__.py
tap_socketdev/__main__.py
tap_socketdev/client.py
tap_socketdev/streams.py
tap_socketdev/tap.py
tap_socketdev-0.4.3.dist-info/METADATA
tap_socketdev-0.4.3.dist-info/WHEEL
tap_socketdev-0.4.3.dist-info/entry_points.txt
tap_socketdev-0.4.3.dist-info/licenses/LICENSE
tap_socketdev-0.4.3.dist-info/RECORD
