Metadata-Version: 2.4
Name: tap-socketdev
Version: 0.4.3
Summary: Singer tap for Socket, built with the Meltano SDK for Singer Taps.
Project-URL: Documentation, https://github.com/reservoir-data/tap-socketdev#readme
Project-URL: Homepage, https://github.com/reservoir-data/tap-socketdev
Project-URL: Repository, https://github.com/reservoir-data/tap-socketdev
Author-email: Edgar Ramírez-Mondragón <edgarrm358@gmail.com>
License-Expression: Apache-2.0
License-File: LICENSE
Keywords: ELT,Socket,singer.io
Classifier: License :: OSI Approved :: Apache Software License
Classifier: Programming Language :: Python :: 3 :: Only
Classifier: Programming Language :: Python :: 3.12
Classifier: Programming Language :: Python :: 3.13
Classifier: Programming Language :: Python :: 3.14
Requires-Python: >=3.12
Requires-Dist: requests~=2.32.0
Requires-Dist: singer-sdk~=0.51.0
